CHANGES.txt
LICENSE.txt
MANIFEST.in
README.txt
setup.py
js/__init__.py
js.jquery_timeago.egg-info/PKG-INFO
js.jquery_timeago.egg-info/SOURCES.txt
js.jquery_timeago.egg-info/dependency_links.txt
js.jquery_timeago.egg-info/entry_points.txt
js.jquery_timeago.egg-info/namespace_packages.txt
js.jquery_timeago.egg-info/not-zip-safe
js.jquery_timeago.egg-info/requires.txt
js.jquery_timeago.egg-info/top_level.txt
js/jquery_timeago/__init__.py
js/jquery_timeago/test_jquery_timeago_plugin.txt
js/jquery_timeago/resources/.git
js/jquery_timeago/resources/.gitignore
js/jquery_timeago/resources/LICENSE.txt
js/jquery_timeago/resources/README.markdown
js/jquery_timeago/resources/clock.png
js/jquery_timeago/resources/index.html
js/jquery_timeago/resources/jquery.timeago.js
js/jquery_timeago/resources/jquery.timeago.jv.js
js/jquery_timeago/resources/timeago.jquery.json
js/jquery_timeago/resources/locales/README.md
js/jquery_timeago/resources/locales/jquery.timeago.ar.js
js/jquery_timeago/resources/locales/jquery.timeago.bg.js
js/jquery_timeago/resources/locales/jquery.timeago.bs.js
js/jquery_timeago/resources/locales/jquery.timeago.ca.js
js/jquery_timeago/resources/locales/jquery.timeago.cy.js
js/jquery_timeago/resources/locales/jquery.timeago.cz.js
js/jquery_timeago/resources/locales/jquery.timeago.da.js
js/jquery_timeago/resources/locales/jquery.timeago.de.js
js/jquery_timeago/resources/locales/jquery.timeago.el.js
js/jquery_timeago/resources/locales/jquery.timeago.en-short.js
js/jquery_timeago/resources/locales/jquery.timeago.en.js
js/jquery_timeago/resources/locales/jquery.timeago.es.js
js/jquery_timeago/resources/locales/jquery.timeago.et.js
js/jquery_timeago/resources/locales/jquery.timeago.fa.js
js/jquery_timeago/resources/locales/jquery.timeago.fi.js
js/jquery_timeago/resources/locales/jquery.timeago.fr-short.js
js/jquery_timeago/resources/locales/jquery.timeago.fr.js
js/jquery_timeago/resources/locales/jquery.timeago.he.js
js/jquery_timeago/resources/locales/jquery.timeago.hr.js
js/jquery_timeago/resources/locales/jquery.timeago.hu.js
js/jquery_timeago/resources/locales/jquery.timeago.hy.js
js/jquery_timeago/resources/locales/jquery.timeago.id.js
js/jquery_timeago/resources/locales/jquery.timeago.is.js
js/jquery_timeago/resources/locales/jquery.timeago.it.js
