Metadata-Version: 1.0
Name: js.jquery-timeago
Version: 1.3.0
Summary: Fanstatic packaging of jQuery timeago plugin
Home-page: https://github.com/dnozay/js.jquery_timeago
Author: Damien Nozay
Author-email: damien.nozay@gmail.com
License: BSD
Platform: UNKNOWN
